caadam/__init__.py
caadam/additive_scaling.py
caadam/caadam.py
caadam/depth_scaling.py
caadam/multiplicative_scaling.py
caadam/scaling_strategy_base.py
caadam-0.1.1.dist-info/METADATA
caadam-0.1.1.dist-info/WHEEL
caadam-0.1.1.dist-info/RECORD
