Metadata-Version: 2.1
Name: caadam
Version: 0.1.1
Summary: Connection Aware Adam
Author: Rémi Genet
Requires-Python: >=3.9,<3.13
Classifier: Programming Language :: Python :: 3
Classifier: Programming Language :: Python :: 3.9
Classifier: Programming Language :: Python :: 3.10
Classifier: Programming Language :: Python :: 3.11
Classifier: Programming Language :: Python :: 3.12
Requires-Dist: keras (>=3.0.0,<4.0)
